setup.py
Dust.egg-info/PKG-INFO
Dust.egg-info/SOURCES.txt
Dust.egg-info/dependency_links.txt
Dust.egg-info/requires.txt
Dust.egg-info/top_level.txt
Dust.egg-info/zip-safe
dust/__init__.py
dust/core/__init__.py
dust/core/data_packet.py
dust/core/dust_packet.py
dust/core/dust_socket.py
dust/core/util.py
dust/crypto/__init__.py
dust/crypto/curve.py
dust/crypto/dust.py
dust/crypto/keys.py
dust/crypto/pyskein.py
dust/crypto/skein512_256.py
dust/crypto/skein512_512.py
dust/crypto/skeinUtil.py
dust/extensions/__init__.py
dust/extensions/lite/__init__.py
dust/extensions/lite/lite_socket.py
dust/extensions/multiplex/__init__.py
dust/extensions/multiplex/lite_multiplex_socket.py
dust/extensions/multiplex/multiplex_packet.py
dust/extensions/multiplex/multiplex_socket.py
dust/extensions/onion/__init__.py
dust/extensions/onion/onion_packet.py
dust/extensions/onion/onion_socket.py
dust/intro/__init__.py
dust/intro/intro.py
dust/intro/intro_packet.py
dust/intro/intro_socket.py
dust/invite/__init__.py
dust/invite/invite.py
dust/invite/invite_packet.py
dust/invite/win32_inet_pton.py
dust/server/__init__.py
dust/server/activeServices.py
dust/server/lite_router.py
dust/server/router.py
dust/services/__init__.py
dust/services/chat/__init__.py
dust/services/chat/chatService.py
dust/services/dustmail/__init__.py
dust/services/dustmail/dustmailClient.py
dust/services/dustmail/dustmailHandler.py
dust/services/dustmail/dustmailService.py
dust/services/dustmail/dustmailbackClient.py
dust/services/dustmail/dustmailbackHandler.py
dust/services/dustmail/dustmailbackService.py
dust/services/dustmail/reader.py
dust/services/dustmail/send.py
dust/services/file/__init__.py
dust/services/file/fileService.py
dust/services/file/file_packet.py
dust/services/file/file_socket.py
dust/services/mail/__init__.py
dust/services/mail/mailService.py
dust/services/tracker/__init__.py
dust/services/tracker/trackbackClient.py
dust/services/tracker/trackbackHandler.py
dust/services/tracker/trackbackService.py
dust/services/tracker/trackerClient.py
dust/services/tracker/trackerHandler.py
dust/services/tracker/trackerService.py
dust/util/__init__.py
dust/util/safethread.py
