Metadata-Version: 1.0
Name: Dust
Version: 0.1a7
Summary: Blocking-resistant network protocol
Home-page: http://github.com/blanu/Dust
Author: Brandon Wiley
Author-email: dust@blanu.net
License: BSD
Keywords: cryptography privacy internet
Platform: UNKNOWN
Classifier: Development Status :: 3 - Alpha
Classifier: Environment :: No Input/Output (Daemon)
Classifier: License :: OSI Approved :: BSD License
Classifier: Programming Language :: Python
Classifier: Intended Audience :: Developers
Classifier: Operating System :: OS Independent
Classifier: Topic :: Internet
Classifier: Topic :: Security :: Cryptography
Classifier: Topic :: Software Development :: Libraries :: Python Modules
